README.txt
setup.cfg
setup.py
TurboMail.egg-info/PKG-INFO
TurboMail.egg-info/SOURCES.txt
TurboMail.egg-info/dependency_links.txt
TurboMail.egg-info/entry_points.txt
TurboMail.egg-info/requires.txt
TurboMail.egg-info/top_level.txt
TurboMail.egg-info/zip-safe
tests/__init__.py
tests/test_address_list.py
tests/test_custom_transport_injection.py
tests/test_debug_transport.py
tests/test_message.py
tests/test_smtp_transport.py
tests/test_tm2_compatibility.py
tests/test_turbogears_config_compatibility.py
tests/test_utf8qp_extension.py
tests/test_wrapped_message.py
turbomail/__init__.py
turbomail/api.py
turbomail/compat.py
turbomail/control.py
turbomail/email_validator.py
turbomail/exceptions.py
turbomail/message.py
turbomail/release.py
turbomail/util.py
turbomail/wrappedmessage.py
turbomail/adapters/__init__.py
turbomail/adapters/tg1.py
turbomail/adapters/tm_pylons.py
turbomail/extensions/__init__.py
turbomail/extensions/logging.py
turbomail/extensions/utf8qp.py
turbomail/managers/__init__.py
turbomail/managers/demand.py
turbomail/managers/immediate.py
turbomail/transports/__init__.py
turbomail/transports/debug.py
turbomail/transports/smtp.py