Metadata-Version: 1.0
Name: TurboMail
Version: 3.0.1
Summary: TurboMail is a mail delivery subsystem and MIME message generation framework for Python.
Home-page: http://www.python-turbomail.org/
Author: Alice Bevan-McGregor
Author-email: alice+turbomail@gothcandy.com
License: MIT
Download-URL: http://cheeseshop.python.org/pypi/TurboMail/
Platform: UNKNOWN
Classifier: Development Status :: 5 - Production/Stable
Classifier: Framework :: TurboGears
Classifier: Intended Audience :: Developers
Classifier: License :: OSI Approved :: MIT License
Classifier: Operating System :: OS Independent
Classifier: Programming Language :: Python
Classifier: Topic :: Communications :: Email
Classifier: Topic :: Software Development :: Libraries :: Python Modules
